cnvrtr/Converter.py
cnvrtr/__init__.py
cnvrtr-1.1.1.dist-info/LICENSE.md
cnvrtr-1.1.1.dist-info/METADATA
cnvrtr-1.1.1.dist-info/WHEEL
cnvrtr-1.1.1.dist-info/top_level.txt
cnvrtr-1.1.1.dist-info/RECORD
