Metadata-Version: 2.1
Name: cnvrtr
Version: 1.1.1
Summary: Different functions to convert between hex, dec bin etc.
Home-page: https://github.com/5f0ne/cnvrtr
Author: 5f0
License: MIT
Classifier: Operating System :: OS Independent 
Classifier: Programming Language :: Python :: 3 
Classifier: License :: OSI Approved :: MIT License 
License-File: LICENSE.md
